lighthousedataextract/__init__.py
lighthousedataextract/light_house_data_extract.py
lighthousedataextract/simple.py
lighthousedataextract-1.0.9.dist-info/LICENSE.txt
lighthousedataextract-1.0.9.dist-info/METADATA
lighthousedataextract-1.0.9.dist-info/WHEEL
lighthousedataextract-1.0.9.dist-info/top_level.txt
lighthousedataextract-1.0.9.dist-info/RECORD
